LICENSE
README.md
setup.py
excel_invoice_to_pdf.egg-info/PKG-INFO
excel_invoice_to_pdf.egg-info/SOURCES.txt
excel_invoice_to_pdf.egg-info/dependency_links.txt
excel_invoice_to_pdf.egg-info/requires.txt
excel_invoice_to_pdf.egg-info/top_level.txt
invoicing/__init__.py
invoicing/invoice.py